biobank/__init__.py
biobank/cli.py
biobank/conf/config.yaml
biobank/config.py
biobank/dataset.py
biobank/dictionary.py
biobank/importers.py
biobank/singleton.py
biobank_tools-0.1.2.dist-info/entry_points.txt
biobank_tools-0.1.2.dist-info/LICENSE
biobank_tools-0.1.2.dist-info/WHEEL
biobank_tools-0.1.2.dist-info/METADATA
biobank_tools-0.1.2.dist-info/RECORD
